src/fastapi_glogger/__init__.py
src/fastapi_glogger/gcp_log_formatter.py
src/fastapi_glogger/logger.py
src/fastapi_glogger/py.typed
src/fastapi_glogger/utils/__init__.py
src/fastapi_glogger/utils/request_utils.py
fastapi_glogger-0.3.0.dist-info/LICENSE
fastapi_glogger-0.3.0.dist-info/METADATA
fastapi_glogger-0.3.0.dist-info/WHEEL
fastapi_glogger-0.3.0.dist-info/RECORD
