Metadata-Version: 2.1
Name: fastapi-glogger
Version: 0.3.0
Summary: fastapi gcp log formatting package
License: MIT
Author: DelfinaCare
Author-email: open-source@delfina.com
Requires-Python: >=3.11,<4.0
Classifier: License :: OSI Approved :: MIT License
Classifier: Programming Language :: Python :: 3
Classifier: Programming Language :: Python :: 3.11
Classifier: Programming Language :: Python :: 3.12
Requires-Dist: fastapi (>=0.112.2,<1.0.0)
Requires-Dist: google (>=3.0.0,<4.0.0)
Requires-Dist: google-api-core (>=2.19.2,<3.0.0)
Requires-Dist: google-auth (>=2.34.0,<3.0.0)
Requires-Dist: google-cloud-logging (>=3.11.2,<4.0.0)
Requires-Dist: grpc-google-iam-v1 (>=0.12.7,<1.0.0)
Requires-Dist: once-py (>=0.0.5,<1.0.0)
Requires-Dist: protobuf (>=4.25.4,<5.0.0)
Requires-Dist: starlette (>=0.38.2,<1.0.0)
Requires-Dist: starlette-context (>=0.3.6,<1.0.0)
Requires-Dist: typing-extensions (>=4.12.2,<5.0.0)
